Workbook

Sheet FSM
A1: 3 Statement Financial Model of Microsoft
E5: Active Case | F5: ='Sensitivity Analysis'!E2 -> 2
D8: Income Statement | E8: 45107 | F8: =EOMONTH(E8,12) -> 45473 | G8: =EOMONTH(F8,12) -> 45838 | H8: =EOMONTH(G8,12) -> 46203 | I8: =EOMONTH(H8,12) -> 46568 | J8: =EOMONTH(I8,12) -> 46934 | K8: =EOMONTH(J8,12) -> 47299 | L8: =EOMONTH(K8,12) -> 47664
D10: Product | E10: 64699 | F10: 64773 | G10: 63946 | H10: =H12*H30 -> 70092.362 | I10: =I12*I30 -> 75908.469 | J10: =J12*J30 -> 82248.383 | K10: =K12*K30 -> 86425.295 | L10: =L12*L30 -> 90361.303
D11: Service and other | E11: 147216 | F11: 180349 | G11: 217778 | H11: =H12*H31 -> 256707.48 | I11: =I12*I31 -> 299911.35 | J11: =J12*J31 -> 351823.5 | K11: =K12*K31 -> 401905.58 | L11: =L12*L31 -> 459010.93
D12: Total Revenue | E12: =E10+E11 -> 211915 | F12: =F10+F11 -> 245122 | G12: =G10+G11 -> 281724 | H12: =G12*(1+H29) -> 326799.84 | I12: =H12*(1+I29) -> 375819.82 | J12: =I12*(1+J29) -> 434071.89 | K12: =J12*(1+K29) -> 488330.87 | L12: =K12*(1+L29) -> 549372.23
D13: Product COGS | E13: 17804 | F13: 15272 | G13: 13501 | H13: =H10*H32 -> 14018.472 | I13: =I10*I32 -> 15181.694 | J13: =J10*J32 -> 16449.677 | K13: =K10*K32 -> 16420.806 | L13: =L10*L32 -> 17168.648
D14: Service and other COGS | E14: 48059 | F14: 58842 | G14: 74330 | H14: =H11*H33 -> 89847.617 | I14: =I11*I33 -> 104968.97 | J14: =J11*J33 -> 126656.46 | K14: =K11*K33 -> 140666.95 | L14: =L11*L33 -> 156063.72
D15: Total COGS | E15: =SUM(E13:E14) -> 65863 | F15: =SUM(F13:F14) -> 74114 | G15: =SUM(G13:G14) -> 87831 | H15: =SUM(H13:H14) -> 103866.09 | I15: =SUM(I13:I14) -> 120150.67 | J15: =SUM(J13:J14) -> 143106.14 | K15: =SUM(K13:K14) -> 157087.76 | L15: =SUM(L13:L14) -> 173232.36
D16: Gross Margin | E16: =E12-E15 -> 146052 | F16: =F12-F15 -> 171008 | G16: =G12-G15 -> 193893 | H16: =H12-H15 -> 222933.75 | I16: =I12-I15 -> 255669.15 | J16: =J12-J15 -> 290965.75 | K16: =K12-K15 -> 331243.11 | L16: =L12-L15 -> 376139.87
D17: R&D | E17: 27195 | F17: 29510 | G17: 32488 | H17: =H12*H34 -> 40849.98 | I17: =I12*I34 -> 46977.477 | J17: =J12*J34 -> 54258.986 | K17: =K12*K34 -> 58599.705 | L17: =L12*L34 -> 65924.668
D18: Sales and marketing | E18: 22759 | F18: 24456 | G18: 25654 | H18: =H12*H35 -> 28451.441 | I18: =I12*I35 -> 31215.877 | J18: =J12*J35 -> 34318.051 | K18: =K12*K35 -> 36654.484 | L18: =L12*L35 -> 39038.805
D19: General and Administration | E19: 7575 | F19: 7609 | G19: 7223 | H19: =H12*H36 -> 7725.0803 | I19: =I12*I36 -> 8132.2027 | J19: =J12*J36 -> 8524.5504 | K19: =K12*K36 -> 8613.4574 | L19: =L12*L36 -> 8591.3952
D20: Operating Income | E20: =E16-SUM(E17:E19) -> 88523 | F20: =F16-SUM(F17:F19) -> 109433 | G20: =G16-SUM(G17:G19) -> 128528 | H20: =H16-SUM(H17:H19) -> 145907.25 | I20: =I16-SUM(I17:I19) -> 169343.59 | J20: =J16-SUM(J17:J19) -> 193864.16 | K20: =K16-SUM(K17:K19) -> 227375.47 | L20: =L16-SUM(L17:L19) -> 262585
D21: Other income(expense), net | E21: 788 | F21: -1646 | G21: -4901 | H21: =H46 -> -6194.36 | I21: =I46 -> -6154.61 | J21: =J46 -> -6048.1 | K21: =K46 -> -5907.4 | L21: =L46 -> -5728.4
D22: Income before taxes | E22: =E20+E21 -> 89311 | F22: =F20+F21 -> 107787 | G22: =G20+G21 -> 123627 | H22: =H20+H21 -> 139712.89 | I22: =I20+I21 -> 163188.98 | J22: =J20+J21 -> 187816.06 | K22: =K20+K21 -> 221468.07 | L22: =L20+L21 -> 256856.6
D23: Provision for income tax | E23: 16950 | F23: 19651 | G23: 21795 | H23: =H22*H37 -> 25539.516 | I23: =I22*I37 -> 29830.946 | J23: =J22*J37 -> 34332.776 | K23: =K22*K37 -> 40484.363 | L23: =L22*L37 -> 46953.387
D24: Net Income | E24: =E22-E23 -> 72361 | F24: =F22-F23 -> 88136 | G24: =G22-G23 -> 101832 | H24: =H22-H23 -> 114173.37 | I24: =I22-I23 -> 133358.04 | J24: =J22-J23 -> 153483.29 | K24: =K22-K23 -> 180983.71 | L24: =L22-L23 -> 209903.21
D29: Revenue Growth | F29: =(F12-E12)/E12 -> 0.15669962 | G29: =(G12-F12)/F12 -> 0.14932156 | H29: ='Sensitivity Analysis'!H9 -> 0.16 | I29: ='Sensitivity Analysis'!I9 -> 0.15 | J29: ='Sensitivity Analysis'!J9 -> 0.155 | K29: ='Sensitivity Analysis'!K9 -> 0.125 | L29: ='Sensitivity Analysis'!L9 -> 0.125 | M29: Step Function
D30: Revenue from Product | E30: =E10/E12 -> 0.30530637 | F30: =F10/F12 -> 0.26424801 | G30: =G10/G12 -> 0.22698102 | H30: =G30-$M$30 -> 0.21448102 | I30: =H30-$M$30 -> 0.20198102 | J30: =I30-$M$30 -> 0.18948102 | K30: =J30-$M$30 -> 0.17698102 | L30: =K30-$M$30 -> 0.16448102 | M30: 0.0125
D31: Revenue from Services and other | E31: =E11/E12 -> 0.69469363 | F31: =F11/F12 -> 0.73575199 | G31: =G11/G12 -> 0.77301898 | H31: =G31+$M$31 -> 0.78551898 | I31: =H31+$M$31 -> 0.79801898 | J31: =I31+$M$31 -> 0.81051898 | K31: =J31+$M$31 -> 0.82301898 | L31: =K31+$M$31 -> 0.83551898 | M31: 0.0125
D32: Product COGS/Product Revenue | E32: =E13/E10 -> 0.275182 | F32: =F13/F10 -> 0.23577725 | G32: =G13/G10 -> 0.21113127 | H32: 0.2 | I32: 0.2 | J32: 0.2 | K32: 0.19 | L32: 0.19
D33: Service and other COGS/Services and other Revenue | E33: =E14/E11 -> 0.32645229 | F33: =F14/F11 -> 0.3262674 | G33: =G14/G11 -> 0.34131088 | H33: ='Sensitivity Analysis'!H10 -> 0.35 | I33: ='Sensitivity Analysis'!I10 -> 0.35 | J33: ='Sensitivity Analysis'!J10 -> 0.36 | K33: ='Sensitivity Analysis'!K10 -> 0.35 | L33: ='Sensitivity Analysis'!L10 -> 0.34
D34: R&D as % of Total Revenue | E34: =E17/E12 -> 0.12832975 | F34: =F17/F12 -> 0.12038903 | G34: =G17/G12 -> 0.11531854 | H34: ='Sensitivity Analysis'!H11 -> 0.125 | I34: ='Sensitivity Analysis'!I11 -> 0.125 | J34: ='Sensitivity Analysis'!J11 -> 0.125 | K34: ='Sensitivity Analysis'!K11 -> 0.12 | L34: ='Sensitivity Analysis'!L11 -> 0.12
D35: Sales and Marketing as % of Total Revenue | E35: =E18/E12 -> 0.10739683 | F35: =F18/F12 -> 0.099770726 | G35: =G18/G12 -> 0.091060754 | H35: =G35-$M$35 -> 0.087060754 | I35: =H35-$M$35 -> 0.083060754 | J35: =I35-$M$35 -> 0.079060754 | K35: =J35-$M$35 -> 0.075060754 | L35: =K35-$M$35 -> 0.071060754 | M35: 0.004
D36: General and Admin as % of Total Revenue | E36: =E19/E12 -> 0.035745464 | F36: =F19/F12 -> 0.031041685 | G36: =G19/G12 -> 0.025638568 | H36: =G36-$M$36 -> 0.023638568 | I36: =H36-$M$36 -> 0.021638568 | J36: =I36-$M$36 -> 0.019638568 | K36: =J36-$M$36 -> 0.017638568 | L36: =K36-$M$36 -> 0.015638568 | M36: 0.002
D37: Tax rate | E37: =E23/E22 -> 0.18978625 | F37: =F23/F22 -> 0.18231327 | G37: =G23/G22 -> 0.17629644 | H37: ='Sensitivity Analysis'!H12 -> 0.1828 | I37: ='Sensitivity Analysis'!I12 -> 0.1828 | J37: ='Sensitivity Analysis'!J12 -> 0.1828 | K37: ='Sensitivity Analysis'!K12 -> 0.1828 | L37: ='Sensitivity Analysis'!L12 -> 0.1828
D39: Other income (expense)net | F39: 45473 | G39: =EOMONTH(F39,12) -> 45838 | H39: =EOMONTH(G39,12) -> 46203 | I39: =EOMONTH(H39,12) -> 46568 | J39: =EOMONTH(I39,12) -> 46934 | K39: =EOMONTH(J39,12) -> 47299 | L39: =EOMONTH(K39,12) -> 47664
D40: interest and dividend income | F40: 3157 | G40: 2647 | H40: 1287 | I40: 1093 | J40: 1210 | K40: 1448 | L40: 1627
D41: interest expense | F41: -2935 | G41: -2385 | H41: =-H175 -> -2318.36 | I41: =-I175 -> -2084.61 | J41: =-J175 -> -2095.1 | K41: =-K175 -> -2192.4 | L41: =-L175 -> -2192.4
D42: net recognized loss on investment | F42: -118 | G42: -349 | H42: -349 | I42: -349 | J42: -349 | K42: -349 | L42: -349
D43: net loss on derivatives | F43: -187 | G43: -260 | H43: -260 | I43: -260 | J43: -260 | K43: -260 | L43: -260
D44: net gain (loss) on foreign currency transaction | F44: -244 | G44: 171 | H44: 171 | I44: 171 | J44: 171 | K44: 171 | L44: 171
D45: other,net | F45: -1319 | G45: -4725 | H45: -4725 | I45: -4725 | J45: -4725 | K45: -4725 | L45: -4725
D46: total | F46: =SUM(F40:F45) -> -1646 | G46: =SUM(G40:G45) -> -4901 | H46: =SUM(H40:H45) -> -6194.36 | I46: =SUM(I40:I45) -> -6154.61 | J46: =SUM(J40:J45) -> -6048.1 | K46: =SUM(K40:K45) -> -5907.4 | L46: =SUM(L40:L45) -> -5728.4
D52: Balance Sheet | E52: 45107 | F52: =EOMONTH(E52,12) -> 45473 | G52: =EOMONTH(F52,12) -> 45838 | H52: =EOMONTH(G52,12) -> 46203 | I52: =EOMONTH(H52,12) -> 46568 | J52: =EOMONTH(I52,12) -> 46934 | K52: =EOMONTH(J52,12) -> 47299 | L52: =EOMONTH(K52,12) -> 47664
D54: Cash and Cash Equivalent | F54: 18315 | G54: 30242 | H54: =G54+H126 -> 39717.876 | I54: =H54+I126 -> 37282.522 | J54: =I54+J126 -> 49757.07 | K54: =J54+K126 -> 60923.562 | L54: =K54+L126 -> 70440.069
C55: N/A | D55: Short term investments | F55: 57228 | G55: 64323 | H55: 64323 | I55: 64323 | J55: 64323 | K55: 64323 | L55: 64323
D56: Accounts receivables | F56: 56924 | G56: 69905 | H56: =H91*H12/365 -> 78490.809 | I56: =I91*I12/365 -> 90264.43 | J56: =J91*J12/365 -> 104255.42 | K56: =K91*K12/365 -> 117287.34 | L56: =L91*L12/365 -> 131948.26
D57: Inventories | F57: 1246 | G57: 938 | H57: =G57*(1+H29) -> 1088.08 | I57: =H57*(1+I29) -> 1251.292 | J57: =I57*(1+J29) -> 1445.2423 | K57: =J57*(1+K29) -> 1625.8975 | L57: =K57*(1+L29) -> 1829.1347 | M57: Grown with Revenue
D58: Other current assets | F58: 26021 | G58: 25723 | H58: 25723 | I58: 25723 | J58: 25723 | K58: 25723 | L58: 25723 | M58: Constant
D59: PPE | F59: 135591 | G59: 204966 | H59: =H155 -> 256277.46 | I59: =I155 -> 316210.83 | J59: =J155 -> 380261.83 | K59: =K155 -> 449979.4 | L59: =L155 -> 530837.18 | M59: PPE Schedule
D60: Operating lease right of use Assets | F60: 18961 | G60: 24823 | H60: =G60*(1+H29) -> 28794.68 | I60: =H60*(1+I29) -> 33113.882 | J60: =I60*(1+J29) -> 38246.534 | K60: =J60*(1+K29) -> 43027.35 | L60: =K60*(1+L29) -> 48405.769 | M60: Grown with Revenue
D61: Equity and other investments | F61: 14600 | G61: 15405 | H61: =AVERAGE($F$61:$G$61) -> 15002.5 | I61: =AVERAGE($F$61:$G$61) -> 15002.5 | J61: =AVERAGE($F$61:$G$61) -> 15002.5 | K61: =AVERAGE($F$61:$G$61) -> 15002.5 | L61: =AVERAGE($F$61:$G$61) -> 15002.5 | M61: Average of FY 24 & 25
C62: N/A | D62: Goodwill | F62: 119220 | G62: 119509 | H62: 119509 | I62: 119509 | J62: 119509 | K62: 119509 | L62: 119509 | M62: Constant
C63: N/A | D63: Intangible assets | F63: 27597 | G63: 22604 | H63: 22604 | I63: 22604 | J63: 22604 | K63: 22604 | L63: 22604 | M63: Constant
D64: Other long term assets | F64: 36460 | G64: 40565 | H64: =G64*(1+H29) -> 47055.4 | I64: =H64*(1+I29) -> 54113.71 | J64: =I64*(1+J29) -> 62501.335 | K64: =J64*(1+K29) -> 70314.002 | L64: =K64*(1+L29) -> 79103.252 | M64: Grown with Revenue
D65: Total Assets | F65: =SUM(F54:F64) -> 512163 | G65: =SUM(G54:G64) -> 619003 | H65: =SUM(H54:H64) -> 698585.8 | I65: =SUM(I54:I64) -> 779398.17 | J65: =SUM(J54:J64) -> 883628.93 | K65: =SUM(K54:K64) -> 990319.05 | L65: =SUM(L54:L64) -> 1109725.2
D68: Accounts payable | F68: 21996 | G68: 27724 | H68: =H15*H92/365 -> 31805.754 | I68: =I15*I92/365 -> 36792.397 | J68: =J15*J92/365 -> 43821.796 | K68: =K15*K92/365 -> 48103.231 | L68: =L15*L92/365 -> 53047.014
D69: Short term debt | F69: 6693 | G69: 0 | H69: 0 | I69: 0 | J69: 0 | K69: 0 | L69: 0
D70: Current portion of long term debt | F70: 2249 | G70: 2999 | H70: 0 | I70: 0 | J70: 0 | K70: 0 | L70: 0
D71: Accrued compensation | F71: 12564 | G71: 13709 | H71: =G71*(1+H29) -> 15902.44 | I71: =H71*(1+I29) -> 18287.806 | J71: =I71*(1+J29) -> 21122.416 | K71: =J71*(1+K29) -> 23762.718 | L71: =K71*(1+L29) -> 26733.058 | M71: Grown with Revenue
D72: Short term income tax | F72: 5017 | G72: 7211 | H72: =H23*H93 -> 7485.1313 | I72: =I23*I93 -> 8742.8653 | J72: =J23*J93 -> 10062.263 | K72: =K23*K93 -> 11865.173 | L72: =L23*L93 -> 13761.117
D73: Short term unearned revenue | F73: 57582 | G73: 64555 | H73: =H12*H94 -> 75826.436 | I73: =I12*I94 -> 87200.401 | J73: =J12*J94 -> 100716.46 | K73: =K12*K94 -> 113306.02 | L73: =L12*L94 -> 127469.27
D74: Other current liability | F74: 19185 | G74: 25020 | H74: =G74*(1+H29) -> 29023.2 | I74: =H74*(1+I29) -> 33376.68 | J74: =I74*(1+J29) -> 38550.065 | K74: =J74*(1+K29) -> 43368.824 | L74: =K74*(1+L29) -> 48789.927 | M74: Grown with Revenue
D75: Long term debt | F75: 42688 | G75: 40152 | H75: =H169 -> 42152 | I75: =I169 -> 37902 | J75: =J169 -> 41902 | K75: =K169 -> 43848 | L75: =L169 -> 43848
C76: N/A | D76: Long term income tax | F76: 27931 | G76: 25986 | H76: 25986 | I76: 25986 | J76: 25986 | K76: 25986 | L76: 25986
D77: Long term unearned revenue | F77: 2602 | G77: 2710 | H77: =H12*H95 -> 3306.3101 | I77: =I12*I95 -> 3802.2566 | J77: =J12*J95 -> 4391.6064 | K77: =K12*K95 -> 4940.5572 | L77: =L12*L95 -> 5558.1269
C78: N/A | D78: Deffered income tax | F78: 2618 | G78: 2835 | H78: 2835 | I78: 2835 | J78: 2835 | K78: 2835 | L78: 2835
D79: Operating lease liability | F79: 15497 | G79: 17437 | H79: =G79*(1+H29) -> 20226.92 | I79: =H79*(1+I29) -> 23260.958 | J79: =I79*(1+J29) -> 26866.406 | K79: =J79*(1+K29) -> 30224.707 | L79: =K79*(1+L29) -> 34002.796 | M79: Grown with Revenue
D80: Other long term liability | F80: 27064 | G80: 45186 | H80: =G80*(1+H29) -> 52415.76 | I80: =H80*(1+I29) -> 60278.124 | J80: =I80*(1+J29) -> 69621.233 | K80: =J80*(1+K29) -> 78323.887 | L80: =K80*(1+L29) -> 88114.373 | M80: Grown with Revenue
D81: Total Liability | F81: =SUM(F68:F80) -> 243686 | G81: =SUM(G68:G80) -> 275524 | H81: =SUM(H68:H80) -> 306964.95 | I81: =SUM(I68:I80) -> 338464.49 | J81: =SUM(J68:J80) -> 385875.25 | K81: =SUM(K68:K80) -> 426564.12 | L81: =SUM(L68:L80) -> 470144.68
D83: Common stock and Paid in capital | F83: 100923 | G83: 109095 | H83: =H193 -> 122984.84 | I83: =I193 -> 138958.16 | J83: =J193 -> 157407.34 | K83: =K193 -> 178162.66 | L83: =L193 -> 201512.41
D84: Retained earnings | F84: 173144 | G84: 237731 | H84: =H187 -> 271983.01 | I84: =I187 -> 305322.52 | J84: =J187 -> 343693.34 | K84: =K187 -> 388939.27 | L84: =L187 -> 441415.07
D85: AOCI | F85: -5590 | G85: -3347 | H85: -3347 | I85: -3347 | J85: -3347 | K85: -3347 | L85: -3347
D86: Shareholder Equity | F86: =SUM(F83:F85) -> 268477 | G86: =SUM(G83:G85) -> 343479 | H86: =SUM(H83:H85) -> 391620.85 | I86: =SUM(I83:I85) -> 440933.68 | J86: =SUM(J83:J85) -> 497753.68 | K86: =SUM(K83:K85) -> 563754.93 | L86: =SUM(L83:L85) -> 639580.48
D89: Balance Check | F89: =ROUND(F65-F81-F86,3) -> 0 | G89: =ROUND(G65-G81-G86,3) -> 0 | H89: =ROUND(H65-H81-H86,3) -> 0 | I89: =ROUND(I65-I81-I86,3) -> 0 | J89: =ROUND(J65-J81-J86,3) -> 0 | K89: =ROUND(K65-K81-K86,3) -> 0 | L89: =ROUND(L65-L81-L86,3) -> 0
D91: DSO | F91: =F56/F12*365 -> 84.762934 | G91: =G56/G12*365 -> 90.568517 | H91: =AVERAGE(F91:G91) -> 87.665726 | I91: =H91 -> 87.665726 | J91: =I91 -> 87.665726 | K91: =J91 -> 87.665726 | L91: =K91 -> 87.665726
D92: DPO | F92: =(F68*365)/F15 -> 108.3269 | G92: =(G68*365)/G15 -> 115.21285 | H92: =AVERAGE(F92:G92) -> 111.76988 | I92: =H92 -> 111.76988 | J92: =I92 -> 111.76988 | K92: =J92 -> 111.76988 | L92: =K92 -> 111.76988
D93: Short term income tax/Total income tax | F93: =F72/F23 -> 0.25530507 | G93: =G72/G23 -> 0.3308557 | H93: =AVERAGE(F93:G93) -> 0.29308039 | I93: =H93 -> 0.29308039 | J93: =I93 -> 0.29308039 | K93: =J93 -> 0.29308039 | L93: =K93 -> 0.29308039
D94: Short term unearned revenue/ Total revenue | F94: =F73/F12 -> 0.2349116 | G94: =G73/G12 -> 0.22914271 | H94: =AVERAGE(F94:G94) -> 0.23202715 | I94: =H94 -> 0.23202715 | J94: =I94 -> 0.23202715 | K94: =J94 -> 0.23202715 | L94: =K94 -> 0.23202715
D95: Long term unearned revenue/ Total revenue | F95: =F77/F12 -> 0.010615122 | G95: =G77/G12 -> 0.0096193438 | H95: =AVERAGE(F95:G95) -> 0.010117233 | I95: =H95 -> 0.010117233 | J95: =I95 -> 0.010117233 | K95: =J95 -> 0.010117233 | L95: =K95 -> 0.010117233
D100: Cash Flow Statement | E100: 45107 | F100: =EOMONTH(E100,12) -> 45473 | G100: =EOMONTH(F100,12) -> 45838 | H100: =EOMONTH(G100,12) -> 46203 | I100: =EOMONTH(H100,12) -> 46568 | J100: =EOMONTH(I100,12) -> 46934 | K100: =EOMONTH(J100,12) -> 47299 | L100: =EOMONTH(K100,12) -> 47664
D102: Net Income | H102: =H24 -> 114173.37 | I102: =I24 -> 133358.04 | J102: =J24 -> 153483.29 | K102: =K24 -> 180983.71 | L102: =L24 -> 209903.21
D103: Stock based compensation | E103: 9611 | F103: 10734 | G103: 11974 | H103: =G103*(1+H29) -> 13889.84 | I103: =H103*(1+I29) -> 15973.316 | J103: =I103*(1+J29) -> 18449.18 | K103: =J103*(1+K29) -> 20755.327 | L103: =K103*(1+L29) -> 23349.743
D104: D&A | E104: 13861 | F104: 22287 | G104: 34153 | H104: =H147 -> 40231.897 | I104: =I147 -> 46782.546 | J104: =J147 -> 51150.047 | K104: =K147 -> 56239.186 | L104: =L147 -> 64621.49
D105: Changes In Working Capital Assets | H105: =-(SUM(H56:H58)-SUM(G56:G58)) -> -8735.8888 | I105: =-(SUM(I56:I58)-SUM(H56:H58)) -> -11936.833 | J105: =-(SUM(J56:J58)-SUM(I56:I58)) -> -14184.937 | K105: =-(SUM(K56:K58)-SUM(J56:J58)) -> -13212.582 | L105: =-(SUM(L56:L58)-SUM(K56:K58)) -> -14864.155
D106: Changes In Working Capital Liabilities | H106: =(H68+SUM(H71:H74))-(G68+SUM(G71:G74)) -> 21823.961 | I106: =(I68+SUM(I71:I74))-(H68+SUM(H71:H74)) -> 24357.189 | J106: =(J68+SUM(J71:J74))-(I68+SUM(I71:I74)) -> 29872.854 | K106: =(K68+SUM(K71:K74))-(J68+SUM(J71:J74)) -> 26132.963 | L106: =(L68+SUM(L71:L74))-(K68+SUM(K71:K74)) -> 29394.422
D107: Changes Operating lease right of use Assets | H107: =-(H60-G60) -> -3971.68 | I107: =-(I60-H60) -> -4319.202 | J107: =-(J60-I60) -> -5132.6517 | K107: =-(K60-J60) -> -4780.8167 | L107: =-(L60-K60) -> -5378.4188
D108: Changes Operating lease liability | H108: =H79-G79 -> 2789.92 | I108: =I79-H79 -> 3034.038 | J108: =J79-I79 -> 3605.4485 | K108: =K79-J79 -> 3358.3008 | L108: =L79-K79 -> 3778.0884
D109: Changes in long term unearned revenue | H109: =H77-G77 -> 596.31013 | I109: =I77-H77 -> 495.94652 | J109: =J77-I77 -> 589.34978 | K109: =K77-J77 -> 548.9508 | L109: =L77-K77 -> 617.56965
D110: Cash Generated From Operations | H110: =SUM(H102:H109) -> 180797.73 | I110: =SUM(I102:I109) -> 207745.04 | J110: =SUM(J102:J109) -> 237832.58 | K110: =SUM(K102:K109) -> 270025.03 | L110: =SUM(L102:L109) -> 311421.95
D112: Repayment of debt | H112: =H168 -> -3000 | I112: =I168 -> -9250 | J112: =J168 -> 0 | K112: =K168 -> -2054 | L112: =L168 -> 0
D113: New debt taken | H113: =H167 -> 5000 | I113: =I167 -> 5000 | J113: =J167 -> 4000 | K113: =K167 -> 4000 | L113: =L167 -> 0
D114: Dividends paid | E114: -19800 | F114: -21771 | G114: -24802 | H114: =-H24*H131 -> -45669.349 | I114: =-I24*I131 -> -53343.215 | J114: =-J24*J131 -> -61393.314 | K114: =-K24*K131 -> -72393.482 | L114: =-L24*L131 -> -83961.286
D115: Stock purchases | E115: -22245 | F115: -17254 | G115: -18420 | H115: =-H24*H132 -> -34252.012 | I115: =-I24*I132 -> -46675.313 | J115: =-J24*J132 -> -53719.15 | K115: =-K24*K132 -> -63344.297 | L115: =-L24*L132 -> -73466.125
D116: Commercial paper | H116: =H69-G69 -> 0 | I116: =I69-H69 -> 0 | J116: =J69-I69 -> 0 | K116: =K69-J69 -> 0 | L116: =L69-K69 -> 0
D117: Change in Current portion of long term debt | H117: =H70-G70 -> -2999 | I117: =I70-H70 -> 0 | J117: =J70-I70 -> 0 | K117: =K70-J70 -> 0 | L117: =L70-K70 -> 0
D118: Change in equity and other investment | H118: =-(H61-G61) -> 402.5 | I118: =-(I61-H61) -> 0 | J118: =-(J61-I61) -> 0 | K118: =-(K61-J61) -> 0 | L118: =-(L61-K61) -> 0
D119: Cash used in investing activity | H119: =SUM(H112:H118) -> -80517.861 | I119: =SUM(I112:I118) -> -104268.53 | J119: =SUM(J112:J118) -> -111112.46 | K119: =SUM(K112:K118) -> -133791.78 | L119: =SUM(L112:L118) -> -157427.41
D121: Purchase of PPE/Capex | E121: -28107 | F121: -44477 | G121: -64551 | H121: =-H24*H133 -> -79921.361 | I121: =-I24*I133 -> -93350.626 | J121: =-J24*J133 -> -99764.136 | K121: =-K24*K133 -> -108590.22 | L121: =-L24*L133 -> -125941.93
D122: Change in non current assets | H122: =-H160 -> -18112.393 | I122: =-I160 -> -20423.602 | J122: =-J160 -> -23824.537 | K122: =-K160 -> -25179.193 | L122: =-L160 -> -28326.593
D123: Change in non current liability | H123: =H80-G80 -> 7229.76 | I123: =I80-H80 -> 7862.364 | J123: =J80-I80 -> 9343.1092 | K123: =K80-J80 -> 8702.6542 | L123: =L80-K80 -> 9790.4859
D124: Cash used in Financing activity | H124: =SUM(H121:H123) -> -90803.994 | I124: =SUM(I121:I123) -> -105911.86 | J124: =SUM(J121:J123) -> -114245.56 | K124: =SUM(K121:K123) -> -125066.76 | L124: =SUM(L121:L123) -> -144478.03
D126: Cash generated by the end of the year | H126: =H110+H119+H124 -> 9475.8764 | I126: =I110+I119+I124 -> -2435.3545 | J126: =J110+J119+J124 -> 12474.548 | K126: =K110+K119+K124 -> 11166.492 | L126: =L110+L119+L124 -> 9516.5073
D131: Payout Ratio (Dividends/Net income) | E131: =-E114/E24 -> 0.27362806 | F131: =-F114/F24 -> 0.24701598 | G131: =-G114/G24 -> 0.24355802 | H131: 0.4 | I131: 0.4 | J131: 0.4 | K131: 0.4 | L131: 0.4
D132: Stock repurchase/Net income | E132: =-E115/E24 -> 0.30741698 | F132: =-F115/F24 -> 0.19576563 | G132: =-G115/G24 -> 0.18088617 | H132: 0.3 | I132: 0.35 | J132: 0.35 | K132: 0.35 | L132: 0.35
D133: Capex/Net income | E133: =-E121/E24 -> 0.38842747 | F133: =-F121/F24 -> 0.50464056 | G133: =-G121/G24 -> 0.63389701 | H133: 0.7 | I133: 0.7 | J133: 0.65 | K133: 0.6 | L133: 0.6
D138: D&A Schedule | E138: 45107 | F138: =EOMONTH(E138,12) -> 45473 | G138: =EOMONTH(F138,12) -> 45838 | H138: =EOMONTH(G138,12) -> 46203 | I138: =EOMONTH(H138,12) -> 46568 | J138: =EOMONTH(I138,12) -> 46934 | K138: =EOMONTH(J138,12) -> 47299 | L138: =EOMONTH(K138,12) -> 47664
D139: Depreciation related to PPE | E139: 11000 | F139: 15200 | G139: 22000 | H139: =-H140*H141 -> 28609.904 | I139: =-I140*I141 -> 33417.254 | J139: =-J140*J141 -> 35713.134 | K139: =-K140*K141 -> 38872.659 | L139: =-L140*L141 -> 45084.147
...

Sheet Sensitivity Analysis
E2: 2 | F2: Active Case
E4: 1 | F4: Best Case
E5: 2 | F5: Street Case
E6: 3 | F6: Weak Case
D8: Sensitivity Analysis | E8: 45107 | F8: =EOMONTH(E8,12) -> 45473 | G8: =EOMONTH(F8,12) -> 45838 | H8: =EOMONTH(G8,12) -> 46203 | I8: =EOMONTH(H8,12) -> 46568 | J8: =EOMONTH(I8,12) -> 46934 | K8: =EOMONTH(J8,12) -> 47299 | L8: =EOMONTH(K8,12) -> 47664
D9: Revenue growth | H9: =CHOOSE($E$2,H16,H17,H18) -> 0.16 | I9: =CHOOSE($E$2,I16,I17,I18) -> 0.15 | J9: =CHOOSE($E$2,J16,J17,J18) -> 0.155 | K9: =CHOOSE($E$2,K16,K17,K18) -> 0.125 | L9: =CHOOSE($E$2,L16,L17,L18) -> 0.125
D10: Service and other COGS/Services and other Revenue | H10: =CHOOSE($E$2,H21,H22,H23) -> 0.35 | I10: =CHOOSE($E$2,I21,I22,I23) -> 0.35 | J10: =CHOOSE($E$2,J21,J22,J23) -> 0.36 | K10: =CHOOSE($E$2,K21,K22,K23) -> 0.35 | L10: =CHOOSE($E$2,L21,L22,L23) -> 0.34
D11: R&D as % of Total Revenue | H11: =CHOOSE($E$2,H26,H27,H28) -> 0.125 | I11: =CHOOSE($E$2,I26,I27,I28) -> 0.125 | J11: =CHOOSE($E$2,J26,J27,J28) -> 0.125 | K11: =CHOOSE($E$2,K26,K27,K28) -> 0.12 | L11: =CHOOSE($E$2,L26,L27,L28) -> 0.12
D12: Tax rate | H12: =CHOOSE($E$2,H31,H32,H33) -> 0.1828 | I12: =CHOOSE($E$2,I31,I32,I33) -> 0.1828 | J12: =CHOOSE($E$2,J31,J32,J33) -> 0.1828 | K12: =CHOOSE($E$2,K31,K32,K33) -> 0.1828 | L12: =CHOOSE($E$2,L31,L32,L33) -> 0.1828
D15: Revenue growth | G15: OFFSET
D16: Best Case | G16: 0.01 | H16: =H17+$G$16 -> 0.17 | I16: =I17+$G$16 -> 0.16 | J16: =J17+$G$16 -> 0.165 | K16: =K17+$G$16 -> 0.135 | L16: =L17+$G$16 -> 0.135
D17: Street Case | H17: 0.16 | I17: 0.15 | J17: 0.155 | K17: 0.125 | L17: 0.125
D18: Weak Case | G18: -0.025 | H18: =H17+$G$18 -> 0.135 | I18: =I17+$G$18 -> 0.125 | J18: =J17+$G$18 -> 0.13 | K18: =K17+$G$18 -> 0.1 | L18: =L17+$G$18 -> 0.1
D20: Service and other COGS/Services and other Revenue
D21: Best Case | G21: -0.025 | H21: =H22+$G$21 -> 0.325 | I21: =I22+$G$21 -> 0.325 | J21: =J22+$G$21 -> 0.335 | K21: =K22+$G$21 -> 0.325 | L21: =L22+$G$21 -> 0.315
D22: Street Case | H22: 0.35 | I22: 0.35 | J22: 0.36 | K22: 0.35 | L22: 0.34
D23: Weak Case | G23: 0.05 | H23: =H22+$G$23 -> 0.4 | I23: =I22+$G$23 -> 0.4 | J23: =J22+$G$23 -> 0.41 | K23: =K22+$G$23 -> 0.4 | L23: =L22+$G$23 -> 0.39
D25: R&D as % of Total Revenue
D26: Best Case | G26: -0.025 | H26: =H27+$G$26 -> 0.1 | I26: =I27+$G$26 -> 0.1 | J26: =J27+$G$26 -> 0.1 | K26: =K27+$G$26 -> 0.095 | L26: =L27+$G$26 -> 0.095
D27: Street Case | H27: 0.125 | I27: 0.125 | J27: 0.125 | K27: 0.12 | L27: 0.12
D28: Weak Case | G28: 0.025 | H28: =H27+$G$28 -> 0.15 | I28: =I27+$G$28 -> 0.15 | J28: =J27+$G$28 -> 0.15 | K28: =K27+$G$28 -> 0.145 | L28: =L27+$G$28 -> 0.145
D30: Tax rate
D31: Best Case | G31: -0.01 | H31: =H32+$G$31 -> 0.1728 | I31: =I32+$G$31 -> 0.1728 | J31: =J32+$G$31 -> 0.1728 | K31: =K32+$G$31 -> 0.1728 | L31: =L32+$G$31 -> 0.1728
D32: Street Case | H32: 0.1828 | I32: 0.1828 | J32: 0.1828 | K32: 0.1828 | L32: 0.1828
D33: Weak Case | G33: 0.025 | H33: =H32+$G$33 -> 0.2078 | I33: =I32+$G$33 -> 0.2078 | J33: =J32+$G$33 -> 0.2078 | K33: =K32+$G$33 -> 0.2078 | L33: =L32+$G$33 -> 0.2078
